{
    "musicList":{
       "electronic":[
            {
                "musicTitle":"faded",
                "musicImage":"./Imgs/covers/Faded.jpg",
                "musicSrc":"./music/Faded.mp3",
                "musicType":"electronic",
                "musicArtist":"allan walker"
            },
            {
                "musicTitle":"sing me to sleep",
                "musicImage":"./Imgs/covers/Sing-me-to-sleep.jpg",
                "musicSrc":"./music/Sing-me-to-sleep.mp3",
                "musicType":"electronic",
                "musicArtist":"allan walker"
            },
            { 
                "musicTitle":"electro light",
                "musicImage":"./Imgs/covers/Electro-light.jpg",
                "musicSrc":"./music/Electro-light.mp3",
                "musicType":"electronic",
                "musicArtist":"NCS"
            },
            {
                "musicTitle":"astronomia",
                "musicImage":"./Imgs/covers/Astronomia.jpg",
                "musicSrc":"./music/Astronomia.mp3",
                "musicType":"electronic",
                "musicArtist":"vincetone & tony igy"
            }
        ],
        "hiphop":[
            { 
                "musicTitle":"arc north",
                "musicImage":"./Imgs/covers/Arc-north.jpg",
                "musicSrc":"./music/Arc-north.mp3",
                "musicType":"hiphop", 
                "musicArtist":"arc north"
            },
            {
                "musicTitle":"alone",
                "musicImage":"./Imgs/covers/Alosa-pacani-Alone.jpg",
                "musicSrc":"./music/Alosa-pacani-Alone.mp3",
                "musicType":"hiphop",           
                "musicArtist":"Alosa pacani"
            },
            {
                "musicTitle":"Chandelier",
                "musicImage":"./Imgs/covers/Veronica-Bravo-Chandelier.jpg",
                "musicSrc":"./music/Veronica-Bravo-Chandelier.mp3",
                "musicType":"hiphop",           
                "musicArtist":"Veronica Bravo"
            }
        ],
        "rock":[
            {
                "musicTitle":"in the end",
                "musicImage":"./Imgs/covers/In-the-End.jpg",
                "musicSrc":"./music/In-the-End.mp4",
                "musicType":"rock", 
                "musicArtist":"linkin park"
            },
            {
                "musicTitle":"bring me to life",
                "musicImage":"./Imgs/covers/Bring-me-to-life.jpg",
                "musicSrc":"./music/bring-me-to-life.mp4",
                "musicType":"rock",
                "musicArtist":"Evanescence"
            },
            {
                "musicTitle":"du hast",
                "musicImage":"./Imgs/covers/Du-hast.jpg",
                "musicSrc":"./music/Du-hast.mp4",
                "musicType":"rock", 
                "musicArtist":"rammstein"
            },
            {
                "musicTitle":"what i believe",
                "musicImage":"./Imgs/covers/What-I-believe.jpg",
                "musicSrc":"./music/What-I-believe.mp4",
                "musicType":"rock",
                "musicArtist":"skillet"
            }
        ],
        "pop":[
            {
                "musicTitle":"love yourself",
                "musicImage":"./Imgs/covers/Love-yourself.jpg",
                "musicSrc":"./music/Love-yourself.mp4",
                "musicType":"pop", 
                "musicArtist":"justin bieber"
            },
            {
                "musicTitle":"without me",
                "musicImage":"./Imgs/covers/Without-me.jpg",
                "musicSrc":"./music/Without-me.mp4",
                "musicType":"pop",
                "musicArtist":"Halsey"
            },
            {
                "musicTitle":"as it was",
                "musicImage":"./Imgs/covers/As-it-was.jpg",
                "musicSrc":"./music/As-it-was.mp4",
                "musicType":"pop", 
                "musicArtist":"Harry Styles"
            }
        ]
    }
}   